smarthome_meterportal/__init__.py
smarthome_meterportal/api/__init__.py
smarthome_meterportal/api/home_assistant_api.py
smarthome_meterportal/api/homey_api.py
smarthome_meterportal/api_client.py
smarthome_meterportal/api_response.py
smarthome_meterportal/configuration.py
smarthome_meterportal/exceptions.py
smarthome_meterportal/models/__init__.py
smarthome_meterportal/models/auth_request.py
smarthome_meterportal/models/auth_response.py
smarthome_meterportal/models/full_request.py
smarthome_meterportal/models/meter_reading_data.py
smarthome_meterportal/models/meter_reading_response.py
smarthome_meterportal/models/meter_reading_response_data.py
smarthome_meterportal/models/meters_response.py
smarthome_meterportal/models/partial_request.py
smarthome_meterportal/py.typed
smarthome_meterportal/rest.py
smarthome_meterportal-1.0.2.dist-info/METADATA
smarthome_meterportal-1.0.2.dist-info/WHEEL
smarthome_meterportal-1.0.2.dist-info/RECORD
