Metadata-Version: 2.3
Name: smarthome_meterportal
Version: 1.0.2
Summary: SmartHome
License: NoLicense
Keywords: OpenAPI,OpenAPI-Generator,SmartHome
Author: OpenAPI Generator Community
Author-email: team@openapitools.org
Requires-Python: >=3.8,<4.0
Classifier: License :: Other/Proprietary License
Classifier: Programming Language :: Python :: 3
Classifier: Programming Language :: Python :: 3.8
Classifier: Programming Language :: Python :: 3.9
Classifier: Programming Language :: Python :: 3.10
Classifier: Programming Language :: Python :: 3.11
Classifier: Programming Language :: Python :: 3.12
Classifier: Programming Language :: Python :: 3.13
Requires-Dist: aiohttp (>=3.8.4)
Requires-Dist: aiohttp-retry (>=2.8.3)
Requires-Dist: pydantic (>=2)
Requires-Dist: python-dateutil (>=2.8.2)
Requires-Dist: typing-extensions (>=4.7.1)
Requires-Dist: urllib3 (>=1.25.3,<3.0.0)
Project-URL: Repository, https://github.com/GIT_USER_ID/GIT_REPO_ID
